autodistill_yolo_world/__init__.py
autodistill_yolo_world/yolo_world_model.py
autodistill_yolo_world-0.1.2.dist-info/METADATA
autodistill_yolo_world-0.1.2.dist-info/WHEEL
autodistill_yolo_world-0.1.2.dist-info/top_level.txt
autodistill_yolo_world-0.1.2.dist-info/RECORD
