Metadata-Version: 2.1
Name: autodistill-yolo-world
Version: 0.1.2
Summary: YOLO World for use with Autodistill
Home-page: https://github.com/autodistill/autodistill-yolo-world
Author: Roboflow
Author-email: support@roboflow.com
Classifier: Programming Language :: Python :: 3
Classifier: Operating System :: OS Independent
Requires-Python: >=3.7
Requires-Dist: supervision
Requires-Dist: autodistill
Requires-Dist: numpy
Requires-Dist: inference[yolo-world] ==0.9.11
Provides-Extra: dev
Requires-Dist: flake8 ; extra == 'dev'
Requires-Dist: black ==22.3.0 ; extra == 'dev'
Requires-Dist: isort ; extra == 'dev'
Requires-Dist: twine ; extra == 'dev'
Requires-Dist: pytest ; extra == 'dev'
Requires-Dist: wheel ; extra == 'dev'
